MANIFEST.in
README.rst
setup.py
aliyun_python_sdk_ossadmin.egg-info/PKG-INFO
aliyun_python_sdk_ossadmin.egg-info/SOURCES.txt
aliyun_python_sdk_ossadmin.egg-info/dependency_links.txt
aliyun_python_sdk_ossadmin.egg-info/requires.txt
aliyun_python_sdk_ossadmin.egg-info/top_level.txt
aliyunsdkossadmin/__init__.py
aliyunsdkossadmin/request/__init__.py
aliyunsdkossadmin/request/v20130712/CreateOssInstanceRequest.py
aliyunsdkossadmin/request/v20130712/GetBucketPolicyRequest.py
aliyunsdkossadmin/request/v20130712/PutBucketLimitRequest.py
aliyunsdkossadmin/request/v20130712/PutBucketPolicyRequest.py
aliyunsdkossadmin/request/v20130712/PutBucketStatusRequest.py
aliyunsdkossadmin/request/v20130712/__init__.py